LICENSE
MANIFEST.in
setup.py
atofido/__init__.py
atofido/app.py
atofido.egg-info/PKG-INFO
atofido.egg-info/SOURCES.txt
atofido.egg-info/dependency_links.txt
atofido.egg-info/requires.txt
atofido.egg-info/top_level.txt
atofido/config/__init__.py
atofido/config/parser.py
atofido/plugins/__init__.py
atofido/plugins/elitetorrent.py
atofido/plugins/mejortorrent.py
bin/atofido