Metadata-Version: 1.0
Name: atofido
Version: 0.1.2
Summary: Atofido is a plugin-based automatic torrent files downloader
Home-page: https://github.com/joanlopez/atofido
Author: Joan López de la Franca Beltran
Author-email: joanjan14@gmail.com
License: MIT
Keywords: downloader,automatic,torrent
Platform: UNKNOWN
